jsonclasses_cli/__init__.py
jsonclasses_cli/version.py
jsonclasses_cli/console/__init__.py
jsonclasses_cli/new/__init__.py
jsonclasses_cli/new/app_content.py
jsonclasses_cli/new/conf_content.py
jsonclasses_cli/new/env_content.py
jsonclasses_cli/new/gitignore_content.py
jsonclasses_cli/new/mypy_content.py
jsonclasses_cli/new/readme_content.py
jsonclasses_cli/new/req_content.py
jsonclasses_cli/package/__init__.py
jsonclasses_cli/package/kotlin.py
jsonclasses_cli/package/swift.py
jsonclasses_cli/package/ts.py
jsonclasses_cli/package/swift/__init__.py
jsonclasses_cli/package/swift/bool_query.py
jsonclasses_cli/package/swift/codable_class.py
jsonclasses_cli/package/swift/codable_enum.py
jsonclasses_cli/package/swift/codable_struct.py
jsonclasses_cli/package/swift/data_class.py
jsonclasses_cli/package/swift/data_enum.py
jsonclasses_cli/package/swift/data_requests_and_clients.py
jsonclasses_cli/package/swift/date_query.py
jsonclasses_cli/package/swift/datetime_query.py
jsonclasses_cli/package/swift/float_query.py
jsonclasses_cli/package/swift/gitignore_content.py
jsonclasses_cli/package/swift/id_query.py
jsonclasses_cli/package/swift/import_lines.py
jsonclasses_cli/package/swift/int_query.py
jsonclasses_cli/package/swift/jtype_to_swift_type.py
jsonclasses_cli/package/swift/link_codable.py
jsonclasses_cli/package/swift/main_program_content.py
jsonclasses_cli/package/swift/package_content.py
jsonclasses_cli/package/swift/readme_content.py
jsonclasses_cli/package/swift/request_manager.py
jsonclasses_cli/package/swift/response.py
jsonclasses_cli/package/swift/session.py
jsonclasses_cli/package/swift/session_input.py
jsonclasses_cli/package/swift/session_items.py
jsonclasses_cli/package/swift/session_manager.py
jsonclasses_cli/package/swift/shared_utils.py
jsonclasses_cli/package/swift/sign_out.py
jsonclasses_cli/package/swift/sort_order.py
jsonclasses_cli/package/swift/string_query.py
jsonclasses_cli/package/swift/unary_sort_order.py
jsonclasses_cli-3.3.0.dist-info/LICENSE
jsonclasses_cli-3.3.0.dist-info/METADATA
jsonclasses_cli-3.3.0.dist-info/WHEEL
jsonclasses_cli-3.3.0.dist-info/entry_points.txt
jsonclasses_cli-3.3.0.dist-info/top_level.txt
jsonclasses_cli-3.3.0.dist-info/RECORD
