Metadata-Version: 2.1
Name: jsonclasses-cli
Version: 3.3.0
Summary: JSONClasses CLI
Home-page: https://github.com/fillmula/jsonclasses-cli
Author: Fillmula Inc.
Author-email: victor.teo@fillmula.com
License: MIT
Platform: UNKNOWN
Requires-Python: >=3.10
License-File: LICENSE
Requires-Dist: click (<9.0.0,>=8.0.3)
Requires-Dist: rich (<11.0.0,>=10.12.0)
Requires-Dist: jsonclasses (<4.0.0,>=3.3.0)
Requires-Dist: jsonclasses-server (<4.0.0,>=3.3.0)
